{
    "module": "Contact",
    "name": "Person",
    "table": "contact_person",
    "importTable": null,
    "parentModel": "",
    "columns": {
        "id": {
            "name": "id",
            "importSource": "",
            "type": "integer",
            "size": 11,
            "required": false,
            "primaryKey": true,
            "autoInc": true,
            "label": "ID",
            "description": "auto incremented ID",
            "validator": "",
            "validatorMessage": "",
            "unit": "",
            "selectListName": "",
            "calculate": "",
            "defaultValue": "",
            "pseudoCalc": "",
            "isLocked": null,
            "searchable": true
        },
        "first_name": {
            "name": "first_name",
            "importSource": "",
            "type": "string",
            "size": null,
            "required": false,
            "primaryKey": false,
            "autoInc": false,
            "label": "First Name",
            "description": "First and middle name(s) of the person",
            "validator": "",
            "validatorMessage": "",
            "unit": "",
            "selectListName": "",
            "calculate": "",
            "defaultValue": "",
            "pseudoCalc": "",
            "isLocked": null,
            "searchable": true
        },
        "last_name": {
            "name": "last_name",
            "importSource": "",
            "type": "string",
            "size": null,
            "required": false,
            "primaryKey": false,
            "autoInc": false,
            "label": "Last Name",
            "description": "Last name of the person",
            "validator": "",
            "validatorMessage": "",
            "unit": "",
            "selectListName": "",
            "calculate": "",
            "defaultValue": "",
            "pseudoCalc": "",
            "isLocked": null,
            "searchable": true
        },
        "full_name": {
            "name": "full_name",
            "importSource": "",
            "type": "pseudo",
            "size": null,
            "required": false,
            "primaryKey": false,
            "autoInc": false,
            "label": "Full Name",
            "description": "",
            "validator": "",
            "validatorMessage": "",
            "unit": "",
            "selectListName": "",
            "calculate": "",
            "defaultValue": "",
            "pseudoCalc": "$model->first_name . ' ' . $model->last_name",
            "isLocked": null,
            "searchable": false
        },
        "title": {
            "name": "title",
            "importSource": "",
            "type": "string",
            "size": null,
            "required": false,
            "primaryKey": false,
            "autoInc": false,
            "label": "Title",
            "description": "Title of the person",
            "validator": "",
            "validatorMessage": "",
            "unit": "",
            "selectListName": "",
            "calculate": "",
            "defaultValue": "",
            "pseudoCalc": "",
            "isLocked": null,
            "searchable": true
        },
        "gender": {
            "name": "gender",
            "importSource": "",
            "type": "string",
            "size": null,
            "required": false,
            "primaryKey": false,
            "autoInc": false,
            "label": "Gender",
            "description": "Gender of the person",
            "validator": "",
            "validatorMessage": "",
            "unit": "",
            "selectListName": "",
            "calculate": "",
            "defaultValue": "",
            "pseudoCalc": "",
            "isLocked": null,
            "searchable": true
        },
        "orcid": {
            "name": "orcid",
            "importSource": "",
            "type": "string",
            "size": null,
            "required": false,
            "primaryKey": false,
            "autoInc": false,
            "label": "Orcid",
            "description": "www.orcid.org",
            "validator": "",
            "validatorMessage": "",
            "unit": "",
            "selectListName": "",
            "calculate": "",
            "defaultValue": "",
            "pseudoCalc": "",
            "isLocked": null,
            "searchable": true
        },
        "phone": {
            "name": "phone",
            "importSource": "",
            "type": "string",
            "size": null,
            "required": false,
            "primaryKey": false,
            "autoInc": false,
            "label": "Phone",
            "description": "Telephone number, office",
            "validator": "",
            "validatorMessage": "",
            "unit": "",
            "selectListName": "",
            "calculate": "",
            "defaultValue": "",
            "pseudoCalc": "",
            "isLocked": null,
            "searchable": true
        },
        "mobile": {
            "name": "mobile",
            "importSource": "",
            "type": "string",
            "size": null,
            "required": false,
            "primaryKey": false,
            "autoInc": false,
            "label": "Mobile Number",
            "description": "Telephone number, mobile",
            "validator": "",
            "validatorMessage": "",
            "unit": "",
            "selectListName": "",
            "calculate": "",
            "defaultValue": "",
            "pseudoCalc": "",
            "isLocked": null,
            "searchable": true
        },
        "email": {
            "name": "email",
            "importSource": "",
            "type": "string",
            "size": null,
            "required": false,
            "primaryKey": false,
            "autoInc": false,
            "label": "Email Address",
            "description": "Email address",
            "validator": "",
            "validatorMessage": "",
            "unit": "",
            "selectListName": "",
            "calculate": "",
            "defaultValue": "",
            "pseudoCalc": "",
            "isLocked": null,
            "searchable": true
        },
        "affiliation": {
            "name": "affiliation",
            "importSource": "",
            "type": "string_multiple",
            "size": null,
            "required": false,
            "primaryKey": false,
            "autoInc": false,
            "label": "Affiliation",
            "description": "Affiliation in organisation",
            "validator": "",
            "validatorMessage": "",
            "unit": "",
            "selectListName": "",
            "calculate": "",
            "defaultValue": "",
            "pseudoCalc": "",
            "isLocked": null,
            "searchable": true
        },
        "comment": {
            "name": "comment",
            "importSource": "",
            "type": "string",
            "size": null,
            "required": false,
            "primaryKey": false,
            "autoInc": false,
            "label": "Additional Information",
            "description": "Comment on the person or address",
            "validator": "",
            "validatorMessage": "",
            "unit": "",
            "selectListName": "",
            "calculate": "",
            "defaultValue": "",
            "pseudoCalc": "",
            "isLocked": null,
            "searchable": true
        },
        "person_acronym": {
            "name": "person_acronym",
            "importSource": "",
            "type": "string",
            "size": null,
            "required": false,
            "primaryKey": false,
            "autoInc": false,
            "label": "Person Acronym",
            "description": "",
            "validator": "",
            "validatorMessage": "",
            "unit": "",
            "selectListName": "",
            "calculate": "",
            "defaultValue": "",
            "pseudoCalc": "",
            "isLocked": null,
            "searchable": true
        },
        "role": {
            "name": "role",
            "importSource": "",
            "type": "string_multiple",
            "size": null,
            "required": false,
            "primaryKey": false,
            "autoInc": false,
            "label": "Role in mDIS",
            "description": "Role(s) of the person in mDIS, e.g. curator, scientist",
            "validator": "",
            "validatorMessage": "",
            "unit": "",
            "selectListName": "",
            "calculate": "",
            "defaultValue": "",
            "pseudoCalc": "",
            "isLocked": null,
            "searchable": true
        }
    },
    "indices": {
        "pk_id": {
            "name": "pk_id",
            "type": "PRIMARY",
            "columns": [
                "id"
            ],
            "isLocked": null
        }
    },
    "relations": [],
    "behaviors": [],
    "createdAt": 1629115064,
    "modifiedAt": 1641476734,
    "generatedAt": 1636701388,
    "fullName": "ContactPerson"
}